{
  "entity": null,
  "aircraft": "entity",
  "ship": "entity",
  "ground vehicle": "entity",
  "facility": "entity",
  "airliner": "aircraft",
  "other aircraft": "aircraft",
  "a220": "airliner",
  "a321": "airliner",
  "a330": "airliner",
  "a350": "airliner",
  "arj21": "airliner",
  "boeing737": "airliner",
  "boeing747": "airliner",
  "boeing777": "airliner",
  "boeing787": "airliner",
  "c919": "airliner",
  "other-airplane": "other aircraft",
  "military ship": "ship",
  "civil ship": "ship",
  "other ship": "ship",
  "warship": "military ship",
  "dry cargo ship": "civil ship",
  "engineering ship": "civil ship",
  "fishing boat": "civil ship",
  "liquid cargo ship": "civil ship",
  "motorboat": "civil ship",
  "passenger ship": "civil ship",
  "tugboat": "civil ship",
  "other-ship": "other ship",
  "public road vehicle": "ground vehicle",
  "logistics vehicle": "ground vehicle",
  "construction vehicle": "ground vehicle",
  "other vehicle": "ground vehicle",
  "bus": "public road vehicle",
  "small car": "public road vehicle",
  "van": "public road vehicle",
  "cargo truck": "logistics vehicle",
  "dump truck": "logistics vehicle",
  "tractor": "logistics vehicle",
  "trailer": "logistics vehicle",
  "truck tractor": "logistics vehicle",
  "excavator": "construction vehicle",
  "other-vehicle": "other vehicle",
  "sports facility": "facility",
  "traffic facility": "facility",
  "baseball field": "sports facility",
  "basketball court": "sports facility",
  "football field": "sports facility",
  "tennis court": "sports facility",
  "bridge": "traffic facility",
  "intersection": "traffic facility",
  "roundabout": "traffic facility"
}